firefox_secure_proxy/constants.py
firefox_secure_proxy/getproxytoken.py
firefox_secure_proxy/login.py
firefox_secure_proxy/token.py
firefox_secure_proxy/utils.py
firefox_secure_proxy-1.1.0.dist-info/LICENSE
firefox_secure_proxy-1.1.0.dist-info/METADATA
firefox_secure_proxy-1.1.0.dist-info/WHEEL
firefox_secure_proxy-1.1.0.dist-info/entry_points.txt
firefox_secure_proxy-1.1.0.dist-info/top_level.txt
firefox_secure_proxy-1.1.0.dist-info/zip-safe
firefox_secure_proxy-1.1.0.dist-info/RECORD
