Metadata-Version: 2.1
Name: firefox-secure-proxy
Version: 1.1.0
Summary: Standalone wrapper for Firefox Secure Proxy
Home-page: https://github.com/Snawoot/firefox-secure-proxy
Author: Vladislav Yarmak
Author-email: vladislav-ex-src@vm-0.com
License: MIT
Platform: UNKNOWN
Classifier: Programming Language :: Python :: 3.5
Classifier: License :: OSI Approved :: MIT License
Classifier: Operating System :: OS Independent
Classifier: Development Status :: 4 - Beta
Classifier: Environment :: Console
Classifier: Intended Audience :: End Users/Desktop
Classifier: Intended Audience :: Other Audience
Classifier: Operating System :: OS Independent
Classifier: Natural Language :: English
Classifier: Topic :: Internet
Classifier: Topic :: Internet :: Proxy Servers
Classifier: Topic :: Utilities
Requires-Python: >=3.5
Requires-Dist: oic
